[
  {
    "id": "09cf494e150548a0",
    "source": "Ars Technica AI",
    "tier": 2,
    "title": "Energy IPOs surge as investors hunt for ways to play AI boom",
    "url": "https://arstechnica.com/information-technology/2026/07/energy-ipos-surge-as-investors-hunt-for-ways-to-play-ai-boom/",
    "published": "2026-07-16T15:48:21+00:00",
    "summary": "Companies coming to market are raising money at fastest pace this century.",
    "fetched_at": "2026-07-16T17:22:13.723887+00:00"
  },
  {
    "id": "714a3c524f203e9b",
    "source": "Ars Technica AI",
    "tier": 2,
    "title": "It's official: EU will force Google to share search data and open up AI on Android",
    "url": "https://arstechnica.com/gadgets/2026/07/its-official-eu-will-force-google-to-share-search-data-and-open-up-ai-on-android/",
    "published": "2026-07-16T20:41:45+00:00",
    "summary": "Google says these changes could endanger user privacy and security.",
    "fetched_at": "2026-07-16T22:35:00.789915+00:00"
  },
  {
    "id": "368a3dfa05d78a0d",
    "source": "Ars Technica AI",
    "tier": 2,
    "title": "xAI can’t deny Grok makes CSAM anymore. So it’s suing users.",
    "url": "https://arstechnica.com/tech-policy/2026/07/xai-cant-deny-grok-makes-csam-anymore-so-its-suing-users/",
    "published": "2026-07-16T20:26:23+00:00",
    "summary": "Elon Musk's xAI files first lawsuit against Grok user accused of making child sex images.",
    "fetched_at": "2026-07-16T22:35:00.789915+00:00"
  },
  {
    "id": "7c4ec74e93c140ae",
    "source": "Ars Technica AI",
    "tier": 2,
    "title": "Fear of humanoid robots spurs human workers to strike at Hyundai auto factory",
    "url": "https://arstechnica.com/ai/2026/07/fear-of-humanoid-robots-spurs-human-workers-to-strike-at-hyundai-auto-factory/",
    "published": "2026-07-16T20:09:48+00:00",
    "summary": "Hyundai aims to deploy 25,000 Atlas robots starting with US factories in 2028.",
    "fetched_at": "2026-07-16T22:35:00.789915+00:00"
  },
  {
    "id": "215b084c997a9e75",
    "source": "Ars Technica AI",
    "tier": 2,
    "title": "Linus Torvalds to critics of AI coding in Linux: \"Fork it. Or just walk away.\"",
    "url": "https://arstechnica.com/ai/2026/07/linus-torvalds-to-critics-of-ai-coding-in-linux-fork-it-or-just-walk-away/",
    "published": "2026-07-16T19:18:23+00:00",
    "summary": "Creator says he will \"very loudly ignore\" those arguing for a ban on AI tools.",
    "fetched_at": "2026-07-16T22:35:00.789915+00:00"
  }
]
